odoo10_addon_dead_mans_switch_client-10.0.1.0.0-py2.7-nspkg.pth
odoo/addons/dead_mans_switch_client/README.rst
odoo/addons/dead_mans_switch_client/__init__.py
odoo/addons/dead_mans_switch_client/__manifest__.py
odoo/addons/dead_mans_switch_client/data/ir_actions.xml
odoo/addons/dead_mans_switch_client/data/ir_cron.xml
odoo/addons/dead_mans_switch_client/demo/dead_mans_switch_client_demo.yml
odoo/addons/dead_mans_switch_client/i18n/am.po
odoo/addons/dead_mans_switch_client/i18n/ca.po
odoo/addons/dead_mans_switch_client/i18n/de.po
odoo/addons/dead_mans_switch_client/i18n/el_GR.po
odoo/addons/dead_mans_switch_client/i18n/es.po
odoo/addons/dead_mans_switch_client/i18n/es_ES.po
odoo/addons/dead_mans_switch_client/i18n/fi.po
odoo/addons/dead_mans_switch_client/i18n/fr.po
odoo/addons/dead_mans_switch_client/i18n/gl.po
odoo/addons/dead_mans_switch_client/i18n/hr.po
odoo/addons/dead_mans_switch_client/i18n/hr_HR.po
odoo/addons/dead_mans_switch_client/i18n/it.po
odoo/addons/dead_mans_switch_client/i18n/nl.po
odoo/addons/dead_mans_switch_client/i18n/pt.po
odoo/addons/dead_mans_switch_client/i18n/pt_BR.po
odoo/addons/dead_mans_switch_client/i18n/pt_PT.po
odoo/addons/dead_mans_switch_client/i18n/sl.po
odoo/addons/dead_mans_switch_client/i18n/tr.po
odoo/addons/dead_mans_switch_client/i18n/zh_CN.po
odoo/addons/dead_mans_switch_client/models/__init__.py
odoo/addons/dead_mans_switch_client/models/dead_mans_switch_client.py
odoo/addons/dead_mans_switch_client/static/description/icon.png
odoo/addons/dead_mans_switch_client/tests/__init__.py
odoo/addons/dead_mans_switch_client/tests/test_dead_mans_switch_client.py
odoo10_addon_dead_mans_switch_client-10.0.1.0.0.dist-info/DESCRIPTION.rst
odoo10_addon_dead_mans_switch_client-10.0.1.0.0.dist-info/METADATA
odoo10_addon_dead_mans_switch_client-10.0.1.0.0.dist-info/RECORD
odoo10_addon_dead_mans_switch_client-10.0.1.0.0.dist-info/WHEEL
odoo10_addon_dead_mans_switch_client-10.0.1.0.0.dist-info/metadata.json
odoo10_addon_dead_mans_switch_client-10.0.1.0.0.dist-info/namespace_packages.txt
odoo10_addon_dead_mans_switch_client-10.0.1.0.0.dist-info/top_level.txt
